<stg><name>Block_for.end_proc</name>


<trans_list>

<trans id="10" from="1" to="2">
<condition id="-1">
<or_exp><and_exp></and_exp></or_exp>
</condition>
</trans>
</trans_list>



<state_list>

<state id="1" st_id="1">

<operation id="3" st_id="1" stage="1" lat="1">
<core>FIFO_SRL</core>
<MemPortIdVec></MemPortIdVec>
<condition id="-1">
<or_exp><and_exp></and_exp></or_exp>
</condition>

<Node id="4" bw="32" op_0_bw="32" op_1_bw="32">
<![CDATA[
entry:1 %p_read_1 = read i32 @_ssdm_op_Read.ap_auto.i32, i32 %p_read

]]></Node>
<StgValue><ssdm name="p_read_1"/></StgValue>
</operation>

<operation id="4" st_id="1" stage="1" lat="1">
<core>NULL</core>
<MemPortIdVec></MemPortIdVec>
<condition id="-1">
<or_exp><and_exp></and_exp></or_exp>
</condition>

<Node id="5" bw="16" op_0_bw="16" op_1_bw="32" op_2_bw="32" op_3_bw="32">
<![CDATA[
entry:2 %acc = partselect i16 @_ssdm_op_PartSelect.i16.i32.i32.i32, i32 %p_read_1, i32 16, i32 31

]]></Node>
<StgValue><ssdm name="acc"/></StgValue>
</operation>

<operation id="5" st_id="1" stage="1" lat="1">
<core>NULL</core>
<MemPortIdVec></MemPortIdVec>
<condition id="-1">
<or_exp><and_exp></and_exp></or_exp>
</condition>

<Node id="6" bw="32" op_0_bw="16">
<![CDATA[
entry:3 %sext_ln84 = sext i16 %acc

]]></Node>
<StgValue><ssdm name="sext_ln84"/></StgValue>
</operation>

<operation id="6" st_id="1" stage="2" lat="2">
<core>axis</core>
<MemPortIdVec></MemPortIdVec>
<condition id="-1">
<or_exp><and_exp></and_exp></or_exp>
</condition>

<Node id="7" bw="0" op_0_bw="0" op_1_bw="32" op_2_bw="32">
<![CDATA[
entry:4 %write_ln85 = write void @_ssdm_op_Write.axis.volatile.i32P128A, i32 %y, i32 %sext_ln84

]]></Node>
<StgValue><ssdm name="write_ln85"/></StgValue>
</operation>
</state>

<state id="2" st_id="2">

<operation id="7" st_id="2" stage="1" lat="1">
<core>NULL</core>
<MemPortIdVec></MemPortIdVec>
<condition id="-1">
<or_exp><and_exp></and_exp></or_exp>
</condition>

<Node id="3" bw="0" op_0_bw="0" op_1_bw="32" op_2_bw="0" op_3_bw="32" op_4_bw="32" op_5_bw="0" op_6_bw="32" op_7_bw="32" op_8_bw="0" op_9_bw="0" op_10_bw="0" op_11_bw="32" op_12_bw="32" op_13_bw="32" op_14_bw="32" op_15_bw="0" op_16_bw="0" op_17_bw="32" op_18_bw="32">
<![CDATA[
entry:0 %specinterface_ln0 = specinterface void @_ssdm_op_SpecInterface, i32 %y, void @empty, i32 1, i32 1, void @empty_0, i32 0, i32 0, void @empty_1, void @empty_1, void @empty_1, i32 0, i32 0, i32 0, i32 0, void @empty_1, void @empty_1, i32 4294967295, i32 0

]]></Node>
<StgValue><ssdm name="specinterface_ln0"/></StgValue>
</operation>

<operation id="8" st_id="2" stage="1" lat="2">
<core>axis</core>
<MemPortIdVec></MemPortIdVec>
<condition id="-1">
<or_exp><and_exp></and_exp></or_exp>
</condition>

<Node id="7" bw="0" op_0_bw="0" op_1_bw="32" op_2_bw="32">
<![CDATA[
entry:4 %write_ln85 = write void @_ssdm_op_Write.axis.volatile.i32P128A, i32 %y, i32 %sext_ln84

]]></Node>
<StgValue><ssdm name="write_ln85"/></StgValue>
</operation>

<operation id="9" st_id="2" stage="1" lat="1">
<core>NULL</core>
<MemPortIdVec></MemPortIdVec>
<condition id="-1">
<or_exp><and_exp></and_exp></or_exp>
</condition>

<Node id="8" bw="0">
<![CDATA[
entry:5 %ret_ln0 = ret

]]></Node>
<StgValue><ssdm name="ret_ln0"/></StgValue>
</operation>
</state>
</state_list>


<ports>
</ports>


<dataflows>
</dataflows>


</stg>
