<?xml version="1.0" encoding="utf-8"?>
<Messages>
	<Message severity="INFO" prefix="[HLS 200-111]" key="HLS_111_966" tag="RUNTIME" content="Finished File checks and directory preparation: CPU user time: 0.03 seconds. CPU system time: 0.01 seconds. Elapsed time: 10.09 seconds; current allocated memory: 753.648 MB." resolution=""/>
	<Message severity="INFO" prefix="[HLS 200-10]" key="HLS_10_1312" tag="" content="Analyzing design file &apos;../FRincon/fir/firTop.cpp&apos; ..." resolution=""/>
	<Message severity="INFO" prefix="[HLS 200-111]" key="HLS_111_966" tag="RUNTIME" content="Finished Source Code Analysis and Preprocessing: CPU user time: 0.52 seconds. CPU system time: 0.77 seconds. Elapsed time: 2.43 seconds; current allocated memory: 754.012 MB." resolution=""/>
	<Message severity="INFO" prefix="[HLS 200-777]" key="HLS 200-777" tag="" content="Using interface defaults for &apos;Vivado&apos; flow target." resolution=""/>
	<Message severity="INFO" prefix="[HLS 214-248]" key="HLS 214-248" tag="" content="Applying array_partition to &apos;_ZZ3firPiS_E9shift_reg&apos;: Complete partitioning on dimension 1. (../FRincon/fir/firTop.cpp:12:0)" resolution=""/>
	<Message severity="WARNING" prefix="[HLS 214-238]" key="HLS 214-238" tag="" content="Unable to apply INTERFACE pragma options on a pass by value struct member field. Consider changing the signature of the struct to a pass by reference or as a pointer. In function &apos;fir(int*, int*)&apos; (../FRincon/fir/firTop.cpp:8:9)" resolution=""/>
	<Message severity="WARNING" prefix="[HLS 214-142]" key="HLS 214-142" tag="VITIS_INTERFACE" content="Implementing stream: may cause mismatch if read and write accesses are not in sequential order on port &apos;y&apos; (../FRincon/fir/firTop.cpp:7:0)" resolution="http://www.xilinx.com/cgi-bin/docs/rdoc?v=2022.2;t=hls+guidance;d=214-142.html"/>
	<Message severity="WARNING" prefix="[HLS 214-142]" key="HLS 214-142" tag="VITIS_INTERFACE" content="Implementing stream: may cause mismatch if read and write accesses are not in sequential order on port &apos;x&apos; (../FRincon/fir/firTop.cpp:7:0)" resolution="http://www.xilinx.com/cgi-bin/docs/rdoc?v=2022.2;t=hls+guidance;d=214-142.html"/>
	<Message severity="INFO" prefix="[HLS 200-111]" key="HLS_111_966" tag="RUNTIME" content="Finished Compiling Optimization and Transform: CPU user time: 6.97 seconds. CPU system time: 0.92 seconds. Elapsed time: 8.76 seconds; current allocated memory: 755.414 MB." resolution=""/>
	<Message severity="INFO" prefix="[HLS 200-111]" key="HLS_111_966" tag="RUNTIME" content="Finished Checking Pragmas: CPU user time: 0 seconds. CPU system time: 0 seconds. Elapsed time: 0 seconds; current allocated memory: 755.414 MB." resolution=""/>
	<Message severity="INFO" prefix="[HLS 200-10]" key="HLS_10_1467" tag="" content="Starting code transformations ..." resolution=""/>
	<Message severity="INFO" prefix="[HLS 200-111]" key="HLS_111_966" tag="RUNTIME" content="Finished Standard Transforms: CPU user time: 0.13 seconds. CPU system time: 0.01 seconds. Elapsed time: 0.18 seconds; current allocated memory: 757.746 MB." resolution=""/>
	<Message severity="INFO" prefix="[HLS 200-10]" key="HLS_10_1472" tag="" content="Checking synthesizability ..." resolution=""/>
	<Message severity="INFO" prefix="[HLS 200-111]" key="HLS_111_966" tag="RUNTIME" content="Finished Checking Synthesizability: CPU user time: 0.07 seconds. CPU system time: 0.02 seconds. Elapsed time: 0.11 seconds; current allocated memory: 758.168 MB." resolution=""/>
	<Message severity="INFO" prefix="[XFORM 203-510]" key="XFORM_AUTO_PIPELINE_STATUS_244" tag="" content="Pipelining loop &apos;Shift_Accum_Loop&apos; (../FRincon/fir/firTop.cpp:16) in function &apos;fir&apos; automatically." resolution=""/>
	<Message severity="INFO" prefix="[HLS 200-111]" key="HLS_111_966" tag="RUNTIME" content="Finished Loop, function and other optimizations: CPU user time: 0.52 seconds. CPU system time: 0.01 seconds. Elapsed time: 0.56 seconds; current allocated memory: 783.742 MB." resolution=""/>
	<Message severity="INFO" prefix="[HLS 200-111]" key="HLS_111_966" tag="RUNTIME" content="Finished Architecture Synthesis: CPU user time: 1.41 seconds. CPU system time: 0.02 seconds. Elapsed time: 1.43 seconds; current allocated memory: 812.371 MB." resolution=""/>
	<Message severity="INFO" prefix="[HLS 200-10]" key="HLS_10_1317" tag="" content="Starting hardware synthesis ..." resolution=""/>
	<Message severity="INFO" prefix="[HLS 200-10]" key="HLS_10_1385" tag="" content="Synthesizing &apos;fir&apos; ..." resolution=""/>
	<Message severity="INFO" prefix="[HLS 200-10]" key="HLS_10_1477" tag="" content="----------------------------------------------------------------" resolution=""/>
	<Message severity="INFO" prefix="[HLS 200-42]" key="HLS_42_1438" tag="" content="-- Implementing module &apos;fir_Pipeline_Shift_Accum_Loop&apos;" resolution=""/>
	<Message severity="INFO" prefix="[HLS 200-10]" key="HLS_10_1478" tag="" content="----------------------------------------------------------------" resolution=""/>
	<Message severity="INFO" prefix="[SCHED 204-11]" key="SCHED_SCHED_STATUS_597" tag="" content="Starting scheduling ..." resolution=""/>
	<Message severity="INFO" prefix="[SCHED 204-61]" key="SCHED_PIPELINING_STATUS_41" tag="" content="Pipelining loop &apos;Shift_Accum_Loop&apos;." resolution=""/>
	<Message severity="INFO" prefix="[HLS 200-1470]" key="HLS 200-1470" tag="SCHEDULE,VITIS_THROUGHPUT" content="Pipelining result : Target II = NA, Final II = 1, Depth = 4, loop &apos;Shift_Accum_Loop&apos;" resolution=""/>
	<Message severity="INFO" prefix="[SCHED 204-11]" key="SCHED_SCHED_STATUS_596" tag="" content="Finished scheduling." resolution=""/>
	<Message severity="INFO" prefix="[HLS 200-111]" key="HLS_111_966" tag="RUNTIME" content="Finished Scheduling: CPU user time: 0.49 seconds. CPU system time: 0.06 seconds. Elapsed time: 0.62 seconds; current allocated memory: 820.816 MB." resolution=""/>
	<Message severity="INFO" prefix="[BIND 205-100]" key="BIND_100_926" tag="" content="Starting micro-architecture generation ..." resolution=""/>
	<Message severity="INFO" prefix="[BIND 205-101]" key="BIND_101_698" tag="" content="Performing variable lifetime analysis." resolution=""/>
	<Message severity="INFO" prefix="[BIND 205-101]" key="BIND_101_697" tag="" content="Exploring resource sharing." resolution=""/>
	<Message severity="INFO" prefix="[BIND 205-101]" key="BIND_101_693" tag="" content="Binding ..." resolution=""/>
	<Message severity="INFO" prefix="[BIND 205-100]" key="BIND_100_925" tag="" content="Finished micro-architecture generation." resolution=""/>
	<Message severity="INFO" prefix="[HLS 200-111]" key="HLS_111_966" tag="RUNTIME" content="Finished Binding: CPU user time: 0.32 seconds. CPU system time: 0.03 seconds. Elapsed time: 0.4 seconds; current allocated memory: 820.816 MB." resolution=""/>
	<Message severity="INFO" prefix="[HLS 200-10]" key="HLS_10_1477" tag="" content="----------------------------------------------------------------" resolution=""/>
	<Message severity="INFO" prefix="[HLS 200-42]" key="HLS_42_1438" tag="" content="-- Implementing module &apos;fir&apos;" resolution=""/>
	<Message severity="INFO" prefix="[HLS 200-10]" key="HLS_10_1478" tag="" content="----------------------------------------------------------------" resolution=""/>
	<Message severity="INFO" prefix="[SCHED 204-11]" key="SCHED_SCHED_STATUS_597" tag="" content="Starting scheduling ..." resolution=""/>
	<Message severity="INFO" prefix="[SCHED 204-11]" key="SCHED_SCHED_STATUS_596" tag="" content="Finished scheduling." resolution=""/>
	<Message severity="INFO" prefix="[HLS 200-111]" key="HLS_111_966" tag="RUNTIME" content="Finished Scheduling: CPU user time: 0.17 seconds. CPU system time: 0 seconds. Elapsed time: 0.45 seconds; current allocated memory: 820.816 MB." resolution=""/>
	<Message severity="INFO" prefix="[BIND 205-100]" key="BIND_100_926" tag="" content="Starting micro-architecture generation ..." resolution=""/>
	<Message severity="INFO" prefix="[BIND 205-101]" key="BIND_101_698" tag="" content="Performing variable lifetime analysis." resolution=""/>
	<Message severity="INFO" prefix="[BIND 205-101]" key="BIND_101_697" tag="" content="Exploring resource sharing." resolution=""/>
	<Message severity="INFO" prefix="[BIND 205-101]" key="BIND_101_693" tag="" content="Binding ..." resolution=""/>
	<Message severity="INFO" prefix="[BIND 205-100]" key="BIND_100_925" tag="" content="Finished micro-architecture generation." resolution=""/>
	<Message severity="INFO" prefix="[HLS 200-111]" key="HLS_111_966" tag="RUNTIME" content="Finished Binding: CPU user time: 0.05 seconds. CPU system time: 0.02 seconds. Elapsed time: 0.11 seconds; current allocated memory: 820.816 MB." resolution=""/>
	<Message severity="INFO" prefix="[HLS 200-10]" key="HLS_10_1483" tag="" content="----------------------------------------------------------------" resolution=""/>
	<Message severity="INFO" prefix="[HLS 200-10]" key="HLS_10_1484" tag="" content="-- Generating RTL for module &apos;fir_Pipeline_Shift_Accum_Loop&apos;" resolution=""/>
	<Message severity="INFO" prefix="[HLS 200-10]" key="HLS_10_1485" tag="" content="----------------------------------------------------------------" resolution=""/>
	<Message severity="WARNING" prefix="[RTGEN 206-101]" key="RTGEN_101_861" tag="" content="Register &apos;fir_int_int_shift_reg&apos; is power-on initialization." resolution=""/>
	<Message severity="WARNING" prefix="[RTGEN 206-101]" key="RTGEN_101_861" tag="" content="Register &apos;fir_int_int_shift_reg_1&apos; is power-on initialization." resolution=""/>
	<Message severity="WARNING" prefix="[RTGEN 206-101]" key="RTGEN_101_861" tag="" content="Register &apos;fir_int_int_shift_reg_2&apos; is power-on initialization." resolution=""/>
	<Message severity="WARNING" prefix="[RTGEN 206-101]" key="RTGEN_101_861" tag="" content="Register &apos;fir_int_int_shift_reg_3&apos; is power-on initialization." resolution=""/>
	<Message severity="WARNING" prefix="[RTGEN 206-101]" key="RTGEN_101_861" tag="" content="Register &apos;fir_int_int_shift_reg_4&apos; is power-on initialization." resolution=""/>
	<Message severity="WARNING" prefix="[RTGEN 206-101]" key="RTGEN_101_861" tag="" content="Register &apos;fir_int_int_shift_reg_5&apos; is power-on initialization." resolution=""/>
	<Message severity="WARNING" prefix="[RTGEN 206-101]" key="RTGEN_101_861" tag="" content="Register &apos;fir_int_int_shift_reg_6&apos; is power-on initialization." resolution=""/>
	<Message severity="WARNING" prefix="[RTGEN 206-101]" key="RTGEN_101_861" tag="" content="Register &apos;fir_int_int_shift_reg_7&apos; is power-on initialization." resolution=""/>
	<Message severity="WARNING" prefix="[RTGEN 206-101]" key="RTGEN_101_861" tag="" content="Register &apos;fir_int_int_shift_reg_8&apos; is power-on initialization." resolution=""/>
	<Message severity="WARNING" prefix="[RTGEN 206-101]" key="RTGEN_101_861" tag="" content="Register &apos;fir_int_int_shift_reg_9&apos; is power-on initialization." resolution=""/>
	<Message severity="WARNING" prefix="[RTGEN 206-101]" key="RTGEN_101_861" tag="" content="Register &apos;p_ZZ3firPiS_E9shift_reg_10&apos; is power-on initialization." resolution=""/>
	<Message severity="WARNING" prefix="[RTGEN 206-101]" key="RTGEN_101_861" tag="" content="Register &apos;p_ZZ3firPiS_E9shift_reg_11&apos; is power-on initialization." resolution=""/>
	<Message severity="WARNING" prefix="[RTGEN 206-101]" key="RTGEN_101_861" tag="" content="Register &apos;p_ZZ3firPiS_E9shift_reg_12&apos; is power-on initialization." resolution=""/>
	<Message severity="WARNING" prefix="[RTGEN 206-101]" key="RTGEN_101_861" tag="" content="Register &apos;p_ZZ3firPiS_E9shift_reg_13&apos; is power-on initialization." resolution=""/>
	<Message severity="WARNING" prefix="[RTGEN 206-101]" key="RTGEN_101_861" tag="" content="Register &apos;p_ZZ3firPiS_E9shift_reg_14&apos; is power-on initialization." resolution=""/>
	<Message severity="WARNING" prefix="[RTGEN 206-101]" key="RTGEN_101_861" tag="" content="Register &apos;p_ZZ3firPiS_E9shift_reg_15&apos; is power-on initialization." resolution=""/>
	<Message severity="WARNING" prefix="[RTGEN 206-101]" key="RTGEN_101_861" tag="" content="Register &apos;p_ZZ3firPiS_E9shift_reg_16&apos; is power-on initialization." resolution=""/>
	<Message severity="WARNING" prefix="[RTGEN 206-101]" key="RTGEN_101_861" tag="" content="Register &apos;p_ZZ3firPiS_E9shift_reg_17&apos; is power-on initialization." resolution=""/>
	<Message severity="WARNING" prefix="[RTGEN 206-101]" key="RTGEN_101_861" tag="" content="Register &apos;p_ZZ3firPiS_E9shift_reg_18&apos; is power-on initialization." resolution=""/>
	<Message severity="WARNING" prefix="[RTGEN 206-101]" key="RTGEN_101_861" tag="" content="Register &apos;p_ZZ3firPiS_E9shift_reg_19&apos; is power-on initialization." resolution=""/>
	<Message severity="WARNING" prefix="[RTGEN 206-101]" key="RTGEN_101_861" tag="" content="Register &apos;p_ZZ3firPiS_E9shift_reg_20&apos; is power-on initialization." resolution=""/>
	<Message severity="WARNING" prefix="[RTGEN 206-101]" key="RTGEN_101_861" tag="" content="Register &apos;p_ZZ3firPiS_E9shift_reg_21&apos; is power-on initialization." resolution=""/>
	<Message severity="WARNING" prefix="[RTGEN 206-101]" key="RTGEN_101_861" tag="" content="Register &apos;p_ZZ3firPiS_E9shift_reg_22&apos; is power-on initialization." resolution=""/>
	<Message severity="WARNING" prefix="[RTGEN 206-101]" key="RTGEN_101_861" tag="" content="Register &apos;p_ZZ3firPiS_E9shift_reg_23&apos; is power-on initialization." resolution=""/>
	<Message severity="WARNING" prefix="[RTGEN 206-101]" key="RTGEN_101_861" tag="" content="Register &apos;p_ZZ3firPiS_E9shift_reg_24&apos; is power-on initialization." resolution=""/>
	<Message severity="WARNING" prefix="[RTGEN 206-101]" key="RTGEN_101_861" tag="" content="Register &apos;p_ZZ3firPiS_E9shift_reg_25&apos; is power-on initialization." resolution=""/>
	<Message severity="WARNING" prefix="[RTGEN 206-101]" key="RTGEN_101_861" tag="" content="Register &apos;p_ZZ3firPiS_E9shift_reg_26&apos; is power-on initialization." resolution=""/>
	<Message severity="WARNING" prefix="[RTGEN 206-101]" key="RTGEN_101_861" tag="" content="Register &apos;p_ZZ3firPiS_E9shift_reg_27&apos; is power-on initialization." resolution=""/>
	<Message severity="WARNING" prefix="[RTGEN 206-101]" key="RTGEN_101_861" tag="" content="Register &apos;p_ZZ3firPiS_E9shift_reg_28&apos; is power-on initialization." resolution=""/>
	<Message severity="WARNING" prefix="[RTGEN 206-101]" key="RTGEN_101_861" tag="" content="Register &apos;p_ZZ3firPiS_E9shift_reg_29&apos; is power-on initialization." resolution=""/>
	<Message severity="WARNING" prefix="[RTGEN 206-101]" key="RTGEN_101_861" tag="" content="Register &apos;p_ZZ3firPiS_E9shift_reg_30&apos; is power-on initialization." resolution=""/>
	<Message severity="WARNING" prefix="[RTGEN 206-101]" key="RTGEN_101_861" tag="" content="Register &apos;p_ZZ3firPiS_E9shift_reg_31&apos; is power-on initialization." resolution=""/>
	<Message severity="WARNING" prefix="[RTGEN 206-101]" key="RTGEN_101_861" tag="" content="Register &apos;p_ZZ3firPiS_E9shift_reg_32&apos; is power-on initialization." resolution=""/>
	<Message severity="WARNING" prefix="[RTGEN 206-101]" key="RTGEN_101_861" tag="" content="Register &apos;p_ZZ3firPiS_E9shift_reg_33&apos; is power-on initialization." resolution=""/>
	<Message severity="WARNING" prefix="[RTGEN 206-101]" key="RTGEN_101_861" tag="" content="Register &apos;p_ZZ3firPiS_E9shift_reg_34&apos; is power-on initialization." resolution=""/>
	<Message severity="WARNING" prefix="[RTGEN 206-101]" key="RTGEN_101_861" tag="" content="Register &apos;p_ZZ3firPiS_E9shift_reg_35&apos; is power-on initialization." resolution=""/>
	<Message severity="WARNING" prefix="[RTGEN 206-101]" key="RTGEN_101_861" tag="" content="Register &apos;p_ZZ3firPiS_E9shift_reg_36&apos; is power-on initialization." resolution=""/>
	<Message severity="WARNING" prefix="[RTGEN 206-101]" key="RTGEN_101_861" tag="" content="Register &apos;p_ZZ3firPiS_E9shift_reg_37&apos; is power-on initialization." resolution=""/>
	<Message severity="WARNING" prefix="[RTGEN 206-101]" key="RTGEN_101_861" tag="" content="Register &apos;p_ZZ3firPiS_E9shift_reg_38&apos; is power-on initialization." resolution=""/>
	<Message severity="WARNING" prefix="[RTGEN 206-101]" key="RTGEN_101_861" tag="" content="Register &apos;p_ZZ3firPiS_E9shift_reg_39&apos; is power-on initialization." resolution=""/>
	<Message severity="WARNING" prefix="[RTGEN 206-101]" key="RTGEN_101_861" tag="" content="Register &apos;p_ZZ3firPiS_E9shift_reg_40&apos; is power-on initialization." resolution=""/>
	<Message severity="WARNING" prefix="[RTGEN 206-101]" key="RTGEN_101_861" tag="" content="Register &apos;p_ZZ3firPiS_E9shift_reg_41&apos; is power-on initialization." resolution=""/>
	<Message severity="WARNING" prefix="[RTGEN 206-101]" key="RTGEN_101_861" tag="" content="Register &apos;p_ZZ3firPiS_E9shift_reg_42&apos; is power-on initialization." resolution=""/>
	<Message severity="WARNING" prefix="[RTGEN 206-101]" key="RTGEN_101_861" tag="" content="Register &apos;p_ZZ3firPiS_E9shift_reg_43&apos; is power-on initialization." resolution=""/>
	<Message severity="WARNING" prefix="[RTGEN 206-101]" key="RTGEN_101_861" tag="" content="Register &apos;p_ZZ3firPiS_E9shift_reg_44&apos; is power-on initialization." resolution=""/>
	<Message severity="WARNING" prefix="[RTGEN 206-101]" key="RTGEN_101_861" tag="" content="Register &apos;p_ZZ3firPiS_E9shift_reg_45&apos; is power-on initialization." resolution=""/>
	<Message severity="WARNING" prefix="[RTGEN 206-101]" key="RTGEN_101_861" tag="" content="Register &apos;p_ZZ3firPiS_E9shift_reg_46&apos; is power-on initialization." resolution=""/>
	<Message severity="WARNING" prefix="[RTGEN 206-101]" key="RTGEN_101_861" tag="" content="Register &apos;p_ZZ3firPiS_E9shift_reg_47&apos; is power-on initialization." resolution=""/>
	<Message severity="WARNING" prefix="[RTGEN 206-101]" key="RTGEN_101_861" tag="" content="Register &apos;p_ZZ3firPiS_E9shift_reg_48&apos; is power-on initialization." resolution=""/>
	<Message severity="WARNING" prefix="[RTGEN 206-101]" key="RTGEN_101_861" tag="" content="Register &apos;p_ZZ3firPiS_E9shift_reg_49&apos; is power-on initialization." resolution=""/>
	<Message severity="WARNING" prefix="[RTGEN 206-101]" key="RTGEN_101_861" tag="" content="Register &apos;p_ZZ3firPiS_E9shift_reg_50&apos; is power-on initialization." resolution=""/>
	<Message severity="WARNING" prefix="[RTGEN 206-101]" key="RTGEN_101_861" tag="" content="Register &apos;p_ZZ3firPiS_E9shift_reg_51&apos; is power-on initialization." resolution=""/>
	<Message severity="WARNING" prefix="[RTGEN 206-101]" key="RTGEN_101_861" tag="" content="Register &apos;p_ZZ3firPiS_E9shift_reg_52&apos; is power-on initialization." resolution=""/>
	<Message severity="WARNING" prefix="[RTGEN 206-101]" key="RTGEN_101_861" tag="" content="Register &apos;p_ZZ3firPiS_E9shift_reg_53&apos; is power-on initialization." resolution=""/>
	<Message severity="WARNING" prefix="[RTGEN 206-101]" key="RTGEN_101_861" tag="" content="Register &apos;p_ZZ3firPiS_E9shift_reg_54&apos; is power-on initialization." resolution=""/>
	<Message severity="WARNING" prefix="[RTGEN 206-101]" key="RTGEN_101_861" tag="" content="Register &apos;p_ZZ3firPiS_E9shift_reg_55&apos; is power-on initialization." resolution=""/>
	<Message severity="WARNING" prefix="[RTGEN 206-101]" key="RTGEN_101_861" tag="" content="Register &apos;p_ZZ3firPiS_E9shift_reg_56&apos; is power-on initialization." resolution=""/>
	<Message severity="WARNING" prefix="[RTGEN 206-101]" key="RTGEN_101_861" tag="" content="Register &apos;p_ZZ3firPiS_E9shift_reg_57&apos; is power-on initialization." resolution=""/>
	<Message severity="WARNING" prefix="[RTGEN 206-101]" key="RTGEN_101_861" tag="" content="Register &apos;p_ZZ3firPiS_E9shift_reg_58&apos; is power-on initialization." resolution=""/>
	<Message severity="WARNING" prefix="[RTGEN 206-101]" key="RTGEN_101_861" tag="" content="Register &apos;p_ZZ3firPiS_E9shift_reg_59&apos; is power-on initialization." resolution=""/>
	<Message severity="WARNING" prefix="[RTGEN 206-101]" key="RTGEN_101_861" tag="" content="Register &apos;p_ZZ3firPiS_E9shift_reg_60&apos; is power-on initialization." resolution=""/>
	<Message severity="WARNING" prefix="[RTGEN 206-101]" key="RTGEN_101_861" tag="" content="Register &apos;p_ZZ3firPiS_E9shift_reg_61&apos; is power-on initialization." resolution=""/>
	<Message severity="WARNING" prefix="[RTGEN 206-101]" key="RTGEN_101_861" tag="" content="Register &apos;p_ZZ3firPiS_E9shift_reg_62&apos; is power-on initialization." resolution=""/>
	<Message severity="WARNING" prefix="[RTGEN 206-101]" key="RTGEN_101_861" tag="" content="Register &apos;p_ZZ3firPiS_E9shift_reg_63&apos; is power-on initialization." resolution=""/>
	<Message severity="WARNING" prefix="[RTGEN 206-101]" key="RTGEN_101_861" tag="" content="Register &apos;p_ZZ3firPiS_E9shift_reg_64&apos; is power-on initialization." resolution=""/>
	<Message severity="WARNING" prefix="[RTGEN 206-101]" key="RTGEN_101_861" tag="" content="Register &apos;p_ZZ3firPiS_E9shift_reg_65&apos; is power-on initialization." resolution=""/>
	<Message severity="WARNING" prefix="[RTGEN 206-101]" key="RTGEN_101_861" tag="" content="Register &apos;p_ZZ3firPiS_E9shift_reg_66&apos; is power-on initialization." resolution=""/>
	<Message severity="WARNING" prefix="[RTGEN 206-101]" key="RTGEN_101_861" tag="" content="Register &apos;p_ZZ3firPiS_E9shift_reg_67&apos; is power-on initialization." resolution=""/>
	<Message severity="WARNING" prefix="[RTGEN 206-101]" key="RTGEN_101_861" tag="" content="Register &apos;p_ZZ3firPiS_E9shift_reg_68&apos; is power-on initialization." resolution=""/>
	<Message severity="WARNING" prefix="[RTGEN 206-101]" key="RTGEN_101_861" tag="" content="Register &apos;p_ZZ3firPiS_E9shift_reg_69&apos; is power-on initialization." resolution=""/>
	<Message severity="WARNING" prefix="[RTGEN 206-101]" key="RTGEN_101_861" tag="" content="Register &apos;p_ZZ3firPiS_E9shift_reg_70&apos; is power-on initialization." resolution=""/>
	<Message severity="WARNING" prefix="[RTGEN 206-101]" key="RTGEN_101_861" tag="" content="Register &apos;p_ZZ3firPiS_E9shift_reg_71&apos; is power-on initialization." resolution=""/>
	<Message severity="WARNING" prefix="[RTGEN 206-101]" key="RTGEN_101_861" tag="" content="Register &apos;p_ZZ3firPiS_E9shift_reg_72&apos; is power-on initialization." resolution=""/>
	<Message severity="WARNING" prefix="[RTGEN 206-101]" key="RTGEN_101_861" tag="" content="Register &apos;p_ZZ3firPiS_E9shift_reg_73&apos; is power-on initialization." resolution=""/>
	<Message severity="WARNING" prefix="[RTGEN 206-101]" key="RTGEN_101_861" tag="" content="Register &apos;p_ZZ3firPiS_E9shift_reg_74&apos; is power-on initialization." resolution=""/>
	<Message severity="WARNING" prefix="[RTGEN 206-101]" key="RTGEN_101_861" tag="" content="Register &apos;p_ZZ3firPiS_E9shift_reg_75&apos; is power-on initialization." resolution=""/>
	<Message severity="WARNING" prefix="[RTGEN 206-101]" key="RTGEN_101_861" tag="" content="Register &apos;p_ZZ3firPiS_E9shift_reg_76&apos; is power-on initialization." resolution=""/>
	<Message severity="WARNING" prefix="[RTGEN 206-101]" key="RTGEN_101_861" tag="" content="Register &apos;p_ZZ3firPiS_E9shift_reg_77&apos; is power-on initialization." resolution=""/>
	<Message severity="WARNING" prefix="[RTGEN 206-101]" key="RTGEN_101_861" tag="" content="Register &apos;p_ZZ3firPiS_E9shift_reg_78&apos; is power-on initialization." resolution=""/>
	<Message severity="WARNING" prefix="[RTGEN 206-101]" key="RTGEN_101_861" tag="" content="Register &apos;p_ZZ3firPiS_E9shift_reg_79&apos; is power-on initialization." resolution=""/>
	<Message severity="WARNING" prefix="[RTGEN 206-101]" key="RTGEN_101_861" tag="" content="Register &apos;p_ZZ3firPiS_E9shift_reg_80&apos; is power-on initialization." resolution=""/>
	<Message severity="WARNING" prefix="[RTGEN 206-101]" key="RTGEN_101_861" tag="" content="Register &apos;p_ZZ3firPiS_E9shift_reg_81&apos; is power-on initialization." resolution=""/>
	<Message severity="WARNING" prefix="[RTGEN 206-101]" key="RTGEN_101_861" tag="" content="Register &apos;p_ZZ3firPiS_E9shift_reg_82&apos; is power-on initialization." resolution=""/>
	<Message severity="WARNING" prefix="[RTGEN 206-101]" key="RTGEN_101_861" tag="" content="Register &apos;p_ZZ3firPiS_E9shift_reg_83&apos; is power-on initialization." resolution=""/>
	<Message severity="WARNING" prefix="[RTGEN 206-101]" key="RTGEN_101_861" tag="" content="Register &apos;p_ZZ3firPiS_E9shift_reg_84&apos; is power-on initialization." resolution=""/>
	<Message severity="WARNING" prefix="[RTGEN 206-101]" key="RTGEN_101_861" tag="" content="Register &apos;p_ZZ3firPiS_E9shift_reg_85&apos; is power-on initialization." resolution=""/>
	<Message severity="WARNING" prefix="[RTGEN 206-101]" key="RTGEN_101_861" tag="" content="Register &apos;p_ZZ3firPiS_E9shift_reg_86&apos; is power-on initialization." resolution=""/>
	<Message severity="WARNING" prefix="[RTGEN 206-101]" key="RTGEN_101_861" tag="" content="Register &apos;p_ZZ3firPiS_E9shift_reg_87&apos; is power-on initialization." resolution=""/>
	<Message severity="WARNING" prefix="[RTGEN 206-101]" key="RTGEN_101_861" tag="" content="Register &apos;p_ZZ3firPiS_E9shift_reg_88&apos; is power-on initialization." resolution=""/>
	<Message severity="WARNING" prefix="[RTGEN 206-101]" key="RTGEN_101_861" tag="" content="Register &apos;p_ZZ3firPiS_E9shift_reg_89&apos; is power-on initialization." resolution=""/>
	<Message severity="WARNING" prefix="[RTGEN 206-101]" key="RTGEN_101_861" tag="" content="Register &apos;p_ZZ3firPiS_E9shift_reg_90&apos; is power-on initialization." resolution=""/>
	<Message severity="WARNING" prefix="[RTGEN 206-101]" key="RTGEN_101_861" tag="" content="Register &apos;p_ZZ3firPiS_E9shift_reg_91&apos; is power-on initialization." resolution=""/>
	<Message severity="WARNING" prefix="[RTGEN 206-101]" key="RTGEN_101_861" tag="" content="Register &apos;p_ZZ3firPiS_E9shift_reg_92&apos; is power-on initialization." resolution=""/>
	<Message severity="WARNING" prefix="[RTGEN 206-101]" key="RTGEN_101_861" tag="" content="Register &apos;p_ZZ3firPiS_E9shift_reg_93&apos; is power-on initialization." resolution=""/>
	<Message severity="WARNING" prefix="[RTGEN 206-101]" key="RTGEN_101_861" tag="" content="Register &apos;p_ZZ3firPiS_E9shift_reg_94&apos; is power-on initialization." resolution=""/>
	<Message severity="WARNING" prefix="[RTGEN 206-101]" key="RTGEN_101_861" tag="" content="Register &apos;p_ZZ3firPiS_E9shift_reg_95&apos; is power-on initialization." resolution=""/>
	<Message severity="WARNING" prefix="[RTGEN 206-101]" key="RTGEN_101_861" tag="" content="Register &apos;p_ZZ3firPiS_E9shift_reg_96&apos; is power-on initialization." resolution=""/>
	<Message severity="WARNING" prefix="[RTGEN 206-101]" key="RTGEN_101_861" tag="" content="Register &apos;p_ZZ3firPiS_E9shift_reg_97&apos; is power-on initialization." resolution=""/>
	<Message severity="WARNING" prefix="[RTGEN 206-101]" key="RTGEN_101_861" tag="" content="Register &apos;p_ZZ3firPiS_E9shift_reg_98&apos; is power-on initialization." resolution=""/>
	<Message severity="WARNING" prefix="[RTGEN 206-101]" key="RTGEN_101_861" tag="" content="Register &apos;p_ZZ3firPiS_E9shift_reg_99&apos; is power-on initialization." resolution=""/>
	<Message severity="WARNING" prefix="[RTGEN 206-101]" key="RTGEN_101_861" tag="" content="Register &apos;p_ZZ3firPiS_E9shift_reg_100&apos; is power-on initialization." resolution=""/>
	<Message severity="WARNING" prefix="[RTGEN 206-101]" key="RTGEN_101_861" tag="" content="Register &apos;p_ZZ3firPiS_E9shift_reg_101&apos; is power-on initialization." resolution=""/>
	<Message severity="WARNING" prefix="[RTGEN 206-101]" key="RTGEN_101_861" tag="" content="Register &apos;p_ZZ3firPiS_E9shift_reg_102&apos; is power-on initialization." resolution=""/>
	<Message severity="WARNING" prefix="[RTGEN 206-101]" key="RTGEN_101_861" tag="" content="Register &apos;p_ZZ3firPiS_E9shift_reg_103&apos; is power-on initialization." resolution=""/>
	<Message severity="WARNING" prefix="[RTGEN 206-101]" key="RTGEN_101_861" tag="" content="Register &apos;p_ZZ3firPiS_E9shift_reg_104&apos; is power-on initialization." resolution=""/>
	<Message severity="WARNING" prefix="[RTGEN 206-101]" key="RTGEN_101_861" tag="" content="Register &apos;p_ZZ3firPiS_E9shift_reg_105&apos; is power-on initialization." resolution=""/>
	<Message severity="WARNING" prefix="[RTGEN 206-101]" key="RTGEN_101_861" tag="" content="Register &apos;p_ZZ3firPiS_E9shift_reg_106&apos; is power-on initialization." resolution=""/>
	<Message severity="WARNING" prefix="[RTGEN 206-101]" key="RTGEN_101_861" tag="" content="Register &apos;p_ZZ3firPiS_E9shift_reg_107&apos; is power-on initialization." resolution=""/>
	<Message severity="WARNING" prefix="[RTGEN 206-101]" key="RTGEN_101_861" tag="" content="Register &apos;p_ZZ3firPiS_E9shift_reg_108&apos; is power-on initialization." resolution=""/>
	<Message severity="WARNING" prefix="[RTGEN 206-101]" key="RTGEN_101_861" tag="" content="Register &apos;p_ZZ3firPiS_E9shift_reg_109&apos; is power-on initialization." resolution=""/>
	<Message severity="WARNING" prefix="[RTGEN 206-101]" key="RTGEN_101_861" tag="" content="Register &apos;p_ZZ3firPiS_E9shift_reg_110&apos; is power-on initialization." resolution=""/>
	<Message severity="WARNING" prefix="[RTGEN 206-101]" key="RTGEN_101_861" tag="" content="Register &apos;p_ZZ3firPiS_E9shift_reg_111&apos; is power-on initialization." resolution=""/>
	<Message severity="WARNING" prefix="[RTGEN 206-101]" key="RTGEN_101_861" tag="" content="Register &apos;p_ZZ3firPiS_E9shift_reg_112&apos; is power-on initialization." resolution=""/>
	<Message severity="WARNING" prefix="[RTGEN 206-101]" key="RTGEN_101_861" tag="" content="Register &apos;p_ZZ3firPiS_E9shift_reg_113&apos; is power-on initialization." resolution=""/>
	<Message severity="WARNING" prefix="[RTGEN 206-101]" key="RTGEN_101_861" tag="" content="Register &apos;p_ZZ3firPiS_E9shift_reg_114&apos; is power-on initialization." resolution=""/>
	<Message severity="WARNING" prefix="[RTGEN 206-101]" key="RTGEN_101_861" tag="" content="Register &apos;p_ZZ3firPiS_E9shift_reg_115&apos; is power-on initialization." resolution=""/>
	<Message severity="WARNING" prefix="[RTGEN 206-101]" key="RTGEN_101_861" tag="" content="Register &apos;p_ZZ3firPiS_E9shift_reg_116&apos; is power-on initialization." resolution=""/>
	<Message severity="WARNING" prefix="[RTGEN 206-101]" key="RTGEN_101_861" tag="" content="Register &apos;p_ZZ3firPiS_E9shift_reg_117&apos; is power-on initialization." resolution=""/>
	<Message severity="WARNING" prefix="[RTGEN 206-101]" key="RTGEN_101_861" tag="" content="Register &apos;p_ZZ3firPiS_E9shift_reg_118&apos; is power-on initialization." resolution=""/>
	<Message severity="WARNING" prefix="[RTGEN 206-101]" key="RTGEN_101_861" tag="" content="Register &apos;p_ZZ3firPiS_E9shift_reg_119&apos; is power-on initialization." resolution=""/>
	<Message severity="WARNING" prefix="[RTGEN 206-101]" key="RTGEN_101_861" tag="" content="Register &apos;p_ZZ3firPiS_E9shift_reg_120&apos; is power-on initialization." resolution=""/>
	<Message severity="WARNING" prefix="[RTGEN 206-101]" key="RTGEN_101_861" tag="" content="Register &apos;p_ZZ3firPiS_E9shift_reg_121&apos; is power-on initialization." resolution=""/>
	<Message severity="WARNING" prefix="[RTGEN 206-101]" key="RTGEN_101_861" tag="" content="Register &apos;p_ZZ3firPiS_E9shift_reg_122&apos; is power-on initialization." resolution=""/>
	<Message severity="WARNING" prefix="[RTGEN 206-101]" key="RTGEN_101_861" tag="" content="Register &apos;p_ZZ3firPiS_E9shift_reg_123&apos; is power-on initialization." resolution=""/>
	<Message severity="WARNING" prefix="[RTGEN 206-101]" key="RTGEN_101_861" tag="" content="Register &apos;p_ZZ3firPiS_E9shift_reg_124&apos; is power-on initialization." resolution=""/>
	<Message severity="WARNING" prefix="[RTGEN 206-101]" key="RTGEN_101_861" tag="" content="Register &apos;p_ZZ3firPiS_E9shift_reg_125&apos; is power-on initialization." resolution=""/>
	<Message severity="WARNING" prefix="[RTGEN 206-101]" key="RTGEN_101_861" tag="" content="Register &apos;p_ZZ3firPiS_E9shift_reg_126&apos; is power-on initialization." resolution=""/>
	<Message severity="WARNING" prefix="[RTGEN 206-101]" key="RTGEN_101_861" tag="" content="Register &apos;p_ZZ3firPiS_E9shift_reg_127&apos; is power-on initialization." resolution=""/>
	<Message severity="WARNING" prefix="[RTGEN 206-101]" key="RTGEN_101_861" tag="" content="Register &apos;p_ZZ3firPiS_E9shift_reg_128&apos; is power-on initialization." resolution=""/>
	<Message severity="WARNING" prefix="[RTGEN 206-101]" key="RTGEN_101_861" tag="" content="Register &apos;p_ZZ3firPiS_E9shift_reg_129&apos; is power-on initialization." resolution=""/>
	<Message severity="WARNING" prefix="[RTGEN 206-101]" key="RTGEN_101_861" tag="" content="Register &apos;p_ZZ3firPiS_E9shift_reg_130&apos; is power-on initialization." resolution=""/>
	<Message severity="WARNING" prefix="[RTGEN 206-101]" key="RTGEN_101_861" tag="" content="Register &apos;p_ZZ3firPiS_E9shift_reg_131&apos; is power-on initialization." resolution=""/>
	<Message severity="WARNING" prefix="[RTGEN 206-101]" key="RTGEN_101_861" tag="" content="Register &apos;p_ZZ3firPiS_E9shift_reg_132&apos; is power-on initialization." resolution=""/>
	<Message severity="WARNING" prefix="[RTGEN 206-101]" key="RTGEN_101_861" tag="" content="Register &apos;p_ZZ3firPiS_E9shift_reg_133&apos; is power-on initialization." resolution=""/>
	<Message severity="WARNING" prefix="[RTGEN 206-101]" key="RTGEN_101_861" tag="" content="Register &apos;p_ZZ3firPiS_E9shift_reg_134&apos; is power-on initialization." resolution=""/>
	<Message severity="WARNING" prefix="[RTGEN 206-101]" key="RTGEN_101_861" tag="" content="Register &apos;p_ZZ3firPiS_E9shift_reg_135&apos; is power-on initialization." resolution=""/>
	<Message severity="WARNING" prefix="[RTGEN 206-101]" key="RTGEN_101_861" tag="" content="Register &apos;p_ZZ3firPiS_E9shift_reg_136&apos; is power-on initialization." resolution=""/>
	<Message severity="WARNING" prefix="[RTGEN 206-101]" key="RTGEN_101_861" tag="" content="Register &apos;p_ZZ3firPiS_E9shift_reg_137&apos; is power-on initialization." resolution=""/>
	<Message severity="WARNING" prefix="[RTGEN 206-101]" key="RTGEN_101_861" tag="" content="Register &apos;p_ZZ3firPiS_E9shift_reg_138&apos; is power-on initialization." resolution=""/>
	<Message severity="WARNING" prefix="[RTGEN 206-101]" key="RTGEN_101_861" tag="" content="Register &apos;p_ZZ3firPiS_E9shift_reg_139&apos; is power-on initialization." resolution=""/>
	<Message severity="WARNING" prefix="[RTGEN 206-101]" key="RTGEN_101_861" tag="" content="Register &apos;p_ZZ3firPiS_E9shift_reg_140&apos; is power-on initialization." resolution=""/>
	<Message severity="WARNING" prefix="[RTGEN 206-101]" key="RTGEN_101_861" tag="" content="Register &apos;p_ZZ3firPiS_E9shift_reg_141&apos; is power-on initialization." resolution=""/>
	<Message severity="WARNING" prefix="[RTGEN 206-101]" key="RTGEN_101_861" tag="" content="Register &apos;p_ZZ3firPiS_E9shift_reg_142&apos; is power-on initialization." resolution=""/>
	<Message severity="WARNING" prefix="[RTGEN 206-101]" key="RTGEN_101_861" tag="" content="Register &apos;p_ZZ3firPiS_E9shift_reg_143&apos; is power-on initialization." resolution=""/>
	<Message severity="WARNING" prefix="[RTGEN 206-101]" key="RTGEN_101_861" tag="" content="Register &apos;p_ZZ3firPiS_E9shift_reg_144&apos; is power-on initialization." resolution=""/>
	<Message severity="WARNING" prefix="[RTGEN 206-101]" key="RTGEN_101_861" tag="" content="Register &apos;p_ZZ3firPiS_E9shift_reg_145&apos; is power-on initialization." resolution=""/>
	<Message severity="WARNING" prefix="[RTGEN 206-101]" key="RTGEN_101_861" tag="" content="Register &apos;p_ZZ3firPiS_E9shift_reg_146&apos; is power-on initialization." resolution=""/>
	<Message severity="WARNING" prefix="[RTGEN 206-101]" key="RTGEN_101_861" tag="" content="Register &apos;p_ZZ3firPiS_E9shift_reg_147&apos; is power-on initialization." resolution=""/>
	<Message severity="WARNING" prefix="[RTGEN 206-101]" key="RTGEN_101_861" tag="" content="Register &apos;p_ZZ3firPiS_E9shift_reg_148&apos; is power-on initialization." resolution=""/>
	<Message severity="WARNING" prefix="[RTGEN 206-101]" key="RTGEN_101_861" tag="" content="Register &apos;p_ZZ3firPiS_E9shift_reg_149&apos; is power-on initialization." resolution=""/>
	<Message severity="WARNING" prefix="[RTGEN 206-101]" key="RTGEN_101_861" tag="" content="Register &apos;p_ZZ3firPiS_E9shift_reg_150&apos; is power-on initialization." resolution=""/>
	<Message severity="WARNING" prefix="[RTGEN 206-101]" key="RTGEN_101_861" tag="" content="Register &apos;p_ZZ3firPiS_E9shift_reg_151&apos; is power-on initialization." resolution=""/>
	<Message severity="WARNING" prefix="[RTGEN 206-101]" key="RTGEN_101_861" tag="" content="Register &apos;p_ZZ3firPiS_E9shift_reg_152&apos; is power-on initialization." resolution=""/>
	<Message severity="WARNING" prefix="[RTGEN 206-101]" key="RTGEN_101_861" tag="" content="Register &apos;p_ZZ3firPiS_E9shift_reg_153&apos; is power-on initialization." resolution=""/>
	<Message severity="WARNING" prefix="[RTGEN 206-101]" key="RTGEN_101_861" tag="" content="Register &apos;p_ZZ3firPiS_E9shift_reg_154&apos; is power-on initialization." resolution=""/>
	<Message severity="WARNING" prefix="[RTGEN 206-101]" key="RTGEN_101_861" tag="" content="Register &apos;p_ZZ3firPiS_E9shift_reg_155&apos; is power-on initialization." resolution=""/>
	<Message severity="WARNING" prefix="[RTGEN 206-101]" key="RTGEN_101_861" tag="" content="Register &apos;p_ZZ3firPiS_E9shift_reg_156&apos; is power-on initialization." resolution=""/>
	<Message severity="WARNING" prefix="[RTGEN 206-101]" key="RTGEN_101_861" tag="" content="Register &apos;p_ZZ3firPiS_E9shift_reg_157&apos; is power-on initialization." resolution=""/>
	<Message severity="WARNING" prefix="[RTGEN 206-101]" key="RTGEN_101_861" tag="" content="Register &apos;p_ZZ3firPiS_E9shift_reg_158&apos; is power-on initialization." resolution=""/>
	<Message severity="WARNING" prefix="[RTGEN 206-101]" key="RTGEN_101_861" tag="" content="Register &apos;p_ZZ3firPiS_E9shift_reg_159&apos; is power-on initialization." resolution=""/>
	<Message severity="WARNING" prefix="[RTGEN 206-101]" key="RTGEN_101_861" tag="" content="Register &apos;p_ZZ3firPiS_E9shift_reg_160&apos; is power-on initialization." resolution=""/>
	<Message severity="WARNING" prefix="[RTGEN 206-101]" key="RTGEN_101_861" tag="" content="Register &apos;p_ZZ3firPiS_E9shift_reg_161&apos; is power-on initialization." resolution=""/>
	<Message severity="WARNING" prefix="[RTGEN 206-101]" key="RTGEN_101_861" tag="" content="Register &apos;p_ZZ3firPiS_E9shift_reg_162&apos; is power-on initialization." resolution=""/>
	<Message severity="WARNING" prefix="[RTGEN 206-101]" key="RTGEN_101_861" tag="" content="Register &apos;p_ZZ3firPiS_E9shift_reg_163&apos; is power-on initialization." resolution=""/>
	<Message severity="WARNING" prefix="[RTGEN 206-101]" key="RTGEN_101_861" tag="" content="Register &apos;p_ZZ3firPiS_E9shift_reg_164&apos; is power-on initialization." resolution=""/>
	<Message severity="WARNING" prefix="[RTGEN 206-101]" key="RTGEN_101_861" tag="" content="Register &apos;p_ZZ3firPiS_E9shift_reg_165&apos; is power-on initialization." resolution=""/>
	<Message severity="WARNING" prefix="[RTGEN 206-101]" key="RTGEN_101_861" tag="" content="Register &apos;p_ZZ3firPiS_E9shift_reg_166&apos; is power-on initialization." resolution=""/>
	<Message severity="WARNING" prefix="[RTGEN 206-101]" key="RTGEN_101_861" tag="" content="Register &apos;p_ZZ3firPiS_E9shift_reg_167&apos; is power-on initialization." resolution=""/>
	<Message severity="WARNING" prefix="[RTGEN 206-101]" key="RTGEN_101_861" tag="" content="Register &apos;p_ZZ3firPiS_E9shift_reg_168&apos; is power-on initialization." resolution=""/>
	<Message severity="WARNING" prefix="[RTGEN 206-101]" key="RTGEN_101_861" tag="" content="Register &apos;p_ZZ3firPiS_E9shift_reg_169&apos; is power-on initialization." resolution=""/>
	<Message severity="WARNING" prefix="[RTGEN 206-101]" key="RTGEN_101_861" tag="" content="Register &apos;p_ZZ3firPiS_E9shift_reg_170&apos; is power-on initialization." resolution=""/>
	<Message severity="WARNING" prefix="[RTGEN 206-101]" key="RTGEN_101_861" tag="" content="Register &apos;p_ZZ3firPiS_E9shift_reg_171&apos; is power-on initialization." resolution=""/>
	<Message severity="WARNING" prefix="[RTGEN 206-101]" key="RTGEN_101_861" tag="" content="Register &apos;p_ZZ3firPiS_E9shift_reg_172&apos; is power-on initialization." resolution=""/>
	<Message severity="WARNING" prefix="[RTGEN 206-101]" key="RTGEN_101_861" tag="" content="Register &apos;p_ZZ3firPiS_E9shift_reg_173&apos; is power-on initialization." resolution=""/>
	<Message severity="WARNING" prefix="[RTGEN 206-101]" key="RTGEN_101_861" tag="" content="Register &apos;p_ZZ3firPiS_E9shift_reg_174&apos; is power-on initialization." resolution=""/>
	<Message severity="WARNING" prefix="[RTGEN 206-101]" key="RTGEN_101_861" tag="" content="Register &apos;p_ZZ3firPiS_E9shift_reg_175&apos; is power-on initialization." resolution=""/>
	<Message severity="WARNING" prefix="[RTGEN 206-101]" key="RTGEN_101_861" tag="" content="Register &apos;p_ZZ3firPiS_E9shift_reg_176&apos; is power-on initialization." resolution=""/>
	<Message severity="WARNING" prefix="[RTGEN 206-101]" key="RTGEN_101_861" tag="" content="Register &apos;p_ZZ3firPiS_E9shift_reg_177&apos; is power-on initialization." resolution=""/>
	<Message severity="WARNING" prefix="[RTGEN 206-101]" key="RTGEN_101_861" tag="" content="Register &apos;p_ZZ3firPiS_E9shift_reg_178&apos; is power-on initialization." resolution=""/>
	<Message severity="WARNING" prefix="[RTGEN 206-101]" key="RTGEN_101_861" tag="" content="Register &apos;p_ZZ3firPiS_E9shift_reg_179&apos; is power-on initialization." resolution=""/>
	<Message severity="INFO" prefix="[HLS 200-1030]" key="HLS 200-1030" tag="" content="Apply Unified Pipeline Control on module &apos;fir_Pipeline_Shift_Accum_Loop&apos; pipeline &apos;Shift_Accum_Loop&apos; pipeline type &apos;loop pipeline&apos;" resolution=""/>
	<Message severity="INFO" prefix="[HLS 200-1552]" key="HLS 200-1552" tag="" content="Enabling free running pipeline (frp) architecture on pipeline &apos;Shift_Accum_Loop&apos; in module &apos;fir_Pipeline_Shift_Accum_Loop&apos;. Estimated max control fanout for pipeline is 6266." resolution=""/>
	<Message severity="INFO" prefix="[RTGEN 206-100]" key="RTGEN_100_855" tag="" content="Generating core module &apos;mul_12s_32s_32_1_1&apos;: 1 instance(s)." resolution=""/>
	<Message severity="INFO" prefix="[RTGEN 206-100]" key="RTGEN_100_855" tag="" content="Generating core module &apos;mux_1818_32_1_1&apos;: 1 instance(s)." resolution=""/>
	<Message severity="INFO" prefix="[RTGEN 206-100]" key="RTGEN_100_856" tag="" content="Finished creating RTL model for &apos;fir_Pipeline_Shift_Accum_Loop&apos;." resolution=""/>
	<Message severity="INFO" prefix="[RTMG 210-279]" key="RTMG_279_1793" tag="" content="Implementing memory &apos;fir_fir_Pipeline_Shift_Accum_Loop_firCoeff_ROM_AUTO_1R&apos; using auto ROMs." resolution=""/>
	<Message severity="INFO" prefix="[HLS 200-111]" key="HLS_111_966" tag="RUNTIME" content="Finished Creating RTL model: CPU user time: 0.77 seconds. CPU system time: 0.17 seconds. Elapsed time: 2.37 seconds; current allocated memory: 821.688 MB." resolution=""/>
	<Message severity="INFO" prefix="[HLS 200-10]" key="HLS_10_1483" tag="" content="----------------------------------------------------------------" resolution=""/>
	<Message severity="INFO" prefix="[HLS 200-10]" key="HLS_10_1484" tag="" content="-- Generating RTL for module &apos;fir&apos;" resolution=""/>
	<Message severity="INFO" prefix="[HLS 200-10]" key="HLS_10_1485" tag="" content="----------------------------------------------------------------" resolution=""/>
	<Message severity="WARNING" prefix="[RTGEN 206-101]" key="RTGEN_101_918" tag="" content="Design contains AXI ports. Reset is fixed to synchronous and active low." resolution=""/>
	<Message severity="INFO" prefix="[RTGEN 206-500]" key="PREPROC_IO_COMP_CONFLICT_1950" tag="" content="Setting interface mode on port &apos;fir/y&apos; to &apos;axis&apos; (register, both mode)." resolution=""/>
	<Message severity="INFO" prefix="[RTGEN 206-500]" key="PREPROC_IO_COMP_CONFLICT_1950" tag="" content="Setting interface mode on port &apos;fir/x&apos; to &apos;axis&apos; (register, both mode)." resolution=""/>
	<Message severity="INFO" prefix="[RTGEN 206-500]" key="PREPROC_IO_COMP_CONFLICT_1950" tag="" content="Setting interface mode on function &apos;fir&apos; to &apos;ap_ctrl_hs&apos;." resolution=""/>
	<Message severity="INFO" prefix="[RTGEN 206-100]" key="RTGEN_100_856" tag="" content="Finished creating RTL model for &apos;fir&apos;." resolution=""/>
	<Message severity="INFO" prefix="[HLS 200-111]" key="HLS_111_966" tag="RUNTIME" content="Finished Creating RTL model: CPU user time: 0.47 seconds. CPU system time: 0.03 seconds. Elapsed time: 0.68 seconds; current allocated memory: 832.668 MB." resolution=""/>
	<Message severity="INFO" prefix="[HLS 200-111]" key="HLS_111_966" tag="RUNTIME" content="Finished Generating all RTL models: CPU user time: 0.53 seconds. CPU system time: 0.06 seconds. Elapsed time: 1.72 seconds; current allocated memory: 836.668 MB." resolution=""/>
	<Message severity="INFO" prefix="[HLS 200-111]" key="HLS_111_966" tag="RUNTIME" content="Finished Updating report files: CPU user time: 0.46 seconds. CPU system time: 0.07 seconds. Elapsed time: 1.32 seconds; current allocated memory: 842.043 MB." resolution=""/>
	<Message severity="INFO" prefix="[VHDL 208-304]" key="VHDL_304_1066" tag="" content="Generating VHDL RTL for fir." resolution=""/>
	<Message severity="INFO" prefix="[VLOG 209-307]" key="VLOG_307_1067" tag="" content="Generating Verilog RTL for fir." resolution=""/>
	<Message severity="INFO" prefix="[HLS 200-790]" key="HLS 200-790" tag="LOOP,VITIS_KERNEL" content="**** Loop Constraint Status: All loop constraints were satisfied." resolution=""/>
	<Message severity="INFO" prefix="[HLS 200-789]" key="HLS 200-789" tag="THROUGHPUT,VITIS_KERNEL" content="**** Estimated Fmax: 161.03 MHz" resolution=""/>
	<Message severity="INFO" prefix="[HLS 200-111]" key="HLS_111_966" tag="RUNTIME" content="Finished Command csynth_design CPU user time: 12.96 seconds. CPU system time: 2.2 seconds. Elapsed time: 21.39 seconds; current allocated memory: 89.035 MB." resolution=""/>
</Messages>
